pypac/__init__.py
pypac/api.py
pypac/os_settings.py
pypac/parser.py
pypac/parser_functions.py
pypac/parser_functions_ex.py
pypac/resolver.py
pypac/wpad.py
pypac-0.17.1.dist-info/licenses/LICENSE
pypac-0.17.1.dist-info/METADATA
pypac-0.17.1.dist-info/WHEEL
pypac-0.17.1.dist-info/top_level.txt
pypac-0.17.1.dist-info/RECORD
