Metadata-Version: 2.4
Name: PyPAC
Version: 0.17.1
Summary: Proxy auto-config and auto-discovery for Python.
Home-page: https://github.com/carsonyl/pypac
Author: Carson Lam
Author-email: 46059+carsonyl@users.noreply.github.com
License: Apache-2.0
Keywords: pypac,pac,proxy,autoconfig,requests
Classifier: Programming Language :: Python :: 2
Classifier: Programming Language :: Python :: 2.7
Classifier: Programming Language :: Python :: 3
Classifier: Programming Language :: Python :: 3.5
Classifier: Programming Language :: Python :: 3.6
Classifier: Programming Language :: Python :: 3.7
Classifier: Programming Language :: Python :: 3.8
Classifier: Programming Language :: Python :: 3.9
Classifier: Programming Language :: Python :: 3.10
Classifier: Programming Language :: Python :: 3.11
Classifier: Programming Language :: Python :: 3.12
Classifier: Programming Language :: Python :: 3.13
Classifier: Topic :: Internet
Classifier: Environment :: Web Environment
Classifier: Intended Audience :: Developers
Classifier: License :: OSI Approved :: Apache Software License
Classifier: Operating System :: OS Independent
Requires-Python: !=3.0.*,!=3.1.*,!=3.2.*,!=3.3.*,!=3.4.*,>=2.7
License-File: LICENSE
Requires-Dist: requests>=2.0.0
Requires-Dist: tldextract>=2.2.3
Requires-Dist: dukpy>=0.2.2
Requires-Dist: pyobjc-framework-SystemConfiguration>=3.2.1; sys_platform == "darwin"
Provides-Extra: socks
Requires-Dist: requests[socks]>=2.10.0; extra == "socks"
Provides-Extra: dev
Requires-Dist: pytest; extra == "dev"
Requires-Dist: pytest-cov; extra == "dev"
Requires-Dist: mock; extra == "dev"
Requires-Dist: wheel; extra == "dev"
Dynamic: license-file
